{"api.md":"ln6PUJQe","base_api.md":"D0YCpCPP","benchmarks.md":"XdE7A5Ea","conventions.md":"Cd9HLLis","ext_ahmc.md":"CKFq6rR3","ext_dynesty.md":"BK0pc8F5","ext_optimization.md":"BirZ6uq2","ext_pigeons.md":"DOIpqeSA","index.md":"yzFpxY2u","interface.md":"yIveQot-","introduction.md":"DwbnLgkv","tutorials_advanced_hybridimaging.md":"tkRl1zey","tutorials_beginner_geometricmodeling.md":"L4N9g_QW","tutorials_beginner_loadingdata.md":"CnnZTRcA","tutorials_index.md":"DlF1nFeS","tutorials_intermediate_closureimaging.md":"C2yvipxa","tutorials_intermediate_polarizedimaging.md":"-HHXNHEE","tutorials_intermediate_stokesiimaging.md":"BheDxIJI","vlbi_imaging_problem.md":"B8yKazn6"}
